peony/__init__.py
peony/backup.py
peony/caddy.py
peony/caddy_settings
peony/docker_manager.py
peony/utils.py
peony/vpn.py
peony/vpn_settings
peony/templates/caddy/Caddyfile
peony/templates/caddy/docker-compose.yaml
peony/templates/caddy/vpn-select.html
peony/templates/vpns/client.conf
peony/templates/vpns/docker-compose.yml
peony/templates/vpns/easy-rsa.vars
peony/templates/vpns/server.conf
thewiw_peony_openvpn-0.1.4.dist-info/METADATA
thewiw_peony_openvpn-0.1.4.dist-info/WHEEL
thewiw_peony_openvpn-0.1.4.dist-info/entry_points.txt
thewiw_peony_openvpn-0.1.4.dist-info/top_level.txt
thewiw_peony_openvpn-0.1.4.dist-info/RECORD
