Metadata-Version: 2.2
Name: thewiw-peony-openvpn
Version: 0.1.4
Summary: A VPN management tool
Author-email: The WiW <contact@thewiw.com>
License: Apache-2.0
Requires-Python: >=3.9
Requires-Dist: docker>=7.1.0
